fastapi_ms_id/__init__.py
fastapi_ms_id/auth_service.py
fastapi_ms_id-0.1.5.dist-info/LICENSE
fastapi_ms_id-0.1.5.dist-info/METADATA
fastapi_ms_id-0.1.5.dist-info/WHEEL
fastapi_ms_id-0.1.5.dist-info/top_level.txt
fastapi_ms_id-0.1.5.dist-info/RECORD
