Metadata-Version: 2.1
Name: fastapi-ms-id
Version: 0.1.5
Summary: Azure AD authentication for Fast API
Home-page: https://github.com/biolimbo/fastapi_ms_id
Author: Santiago Forero Molano
Author-email: santiago.forero.molano@gmail.com
License: MIT
Classifier: Development Status :: 2 - Pre-Alpha
Classifier: License :: OSI Approved :: MIT License
Classifier: Programming Language :: Python
Classifier: Programming Language :: Python :: 3
Classifier: Programming Language :: Python :: 3.7
Classifier: Programming Language :: Python :: 3.8
Classifier: Programming Language :: Python :: 3.9
Classifier: Programming Language :: Python :: 3.10
License-File: LICENSE
Requires-Dist: fastapi
Requires-Dist: httpx
Requires-Dist: requests
Requires-Dist: python-jose
Requires-Dist: pytest
Requires-Dist: multidict
